app.py
hf_cleaner/__init__.py
hf_cleaner/templates/BaseTemplate.py
hf_cleaner/templates/DefaultTemplate.py
hf_cleaner/templates/__init__.py
hf_cleaner/utils/__init__.py
hf_cleaner/utils/constants.py
hf_cleaner/utils/file_utils.py
run_app.py
hf_cleaner-0.1.1.dist-info/LICENSE
hf_cleaner-0.1.1.dist-info/METADATA
hf_cleaner-0.1.1.dist-info/WHEEL
hf_cleaner-0.1.1.dist-info/entry_points.txt
hf_cleaner-0.1.1.dist-info/RECORD
